{
  "$schema": "https://developer.microsoft.com/json-schemas/fabric/item/report/definition/visualContainer/1.6.0/schema.json",
  "name": "6f018e5a33332620e0aa",
  "position": {
    "x": 34.995857497928746,
    "y": 0,
    "z": 9000,
    "height": 91.2013256006628,
    "width": 44.540182270091137,
    "tabOrder": 81000
  },
  "visual": {
    "visualType": "textbox",
    "objects": {
      "general": [
        {
          "properties": {
            "paragraphs": [
              {
                "textRuns": [
                  {
                    "value": "MAC",
                    "textStyle": {
                      "fontWeight": "bold",
                      "fontFamily": "DIN",
                      "fontSize": "9pt",
                      "color": "#ffffff"
                    }
                  }
                ]
              },
              {
                "textRuns": [
                  {
                    "value": "Sonora",
                    "textStyle": {
                      "fontWeight": "bold",
                      "fontFamily": "DIN",
                      "fontSize": "9pt",
                      "color": "#ffffff"
                    }
                  }
                ]
              },
              {
                "textRuns": [
                  {
                    "value": "CM",
                    "textStyle": {
                      "fontWeight": "bold",
                      "fontFamily": "DIN",
                      "fontSize": "9pt",
                      "color": "#ffffff"
                    }
                  }
                ]
              }
            ]
          }
        }
      ]
    },
    "visualContainerObjects": {
      "background": [
        {
          "properties": {
            "color": {
              "solid": {
                "color": {
                  "expr": {
                    "Literal": {
                      "Value": "'#939393'"
                    }
                  }
                }
              }
            },
            "show": {
              "expr": {
                "Literal": {
                  "Value": "false"
                }
              }
            }
          }
        }
      ]
    },
    "drillFilterOtherVisuals": true
  },
  "parentGroupName": "f4fad74d456901c67bd0"
}